<Root>
    <CKSetup>
        <BinPaths>
            <BinPath>{binPath}</BinPath>
        </BinPaths>
        <EngineAssemblyQualifiedName>CK.Setup.StObjEngine, CK.StObj.Engine</EngineAssemblyQualifiedName>
    </CKSetup>
    <StObjEngineConfiguration>
        <GeneratedAssemblyName>GenByCKSetup</GeneratedAssemblyName>
        <Aspect Type="CK.Setup.SetupableAspectConfiguration, CK.Setupable.Model" />
        <Aspect Type="CK.Setup.SqlSetupAspectConfiguration, CK.SqlServer.Setup.Model" >
            <DefaultDatabaseConnectionString>{connectionString}</DefaultDatabaseConnectionString>
        </Aspect>
    </StObjEngineConfiguration>
</Root>
